univi/__init__.py
univi/__main__.py
univi/cli.py
univi/config.py
univi/data.py
univi/diagnostics.py
univi/evaluation.py
univi/interpretability.py
univi/matching.py
univi/objectives.py
univi/pipeline.py
univi/plotting.py
univi/trainer.py
univi/hyperparam_optimization/__init__.py
univi/hyperparam_optimization/common.py
univi/hyperparam_optimization/run_adt_hparam_search.py
univi/hyperparam_optimization/run_atac_hparam_search.py
univi/hyperparam_optimization/run_citeseq_hparam_search.py
univi/hyperparam_optimization/run_multiome_hparam_search.py
univi/hyperparam_optimization/run_rna_hparam_search.py
univi/hyperparam_optimization/run_teaseq_hparam_search.py
univi/models/__init__.py
univi/models/decoders.py
univi/models/encoders.py
univi/models/mlp.py
univi/models/tokenizers.py
univi/models/transformer.py
univi/models/univi.py
univi/utils/__init__.py
univi/utils/io.py
univi/utils/logging.py
univi/utils/seed.py
univi/utils/stats.py
univi/utils/torch_utils.py
univi-0.3.9.dist-info/licenses/LICENSE
univi-0.3.9.dist-info/METADATA
univi-0.3.9.dist-info/WHEEL
univi-0.3.9.dist-info/entry_points.txt
univi-0.3.9.dist-info/top_level.txt
univi-0.3.9.dist-info/RECORD
