Metadata-Version: 2.4
Name: univi
Version: 0.3.9
Summary: UniVI: a scalable multi-modal variational autoencoder toolkit for seamless integration and analysis of multimodal single-cell data.
Author-email: "Andrew J. Ashford" <ashforda@ohsu.edu>
License: MIT License
Project-URL: Homepage, https://github.com/Ashford-A/UniVI
Project-URL: Repository, https://github.com/Ashford-A/UniVI
Project-URL: Bug Tracker, https://github.com/Ashford-A/UniVI/issues
Classifier: License :: OSI Approved :: MIT License
Classifier: Programming Language :: Python :: 3
Classifier: Programming Language :: Python :: 3.10
Classifier: Programming Language :: Python :: 3 :: Only
Requires-Python: >=3.10
License-File: LICENSE
Requires-Dist: numpy>=1.26
Requires-Dist: scipy>=1.11
Requires-Dist: pandas>=2.1
Requires-Dist: anndata>=0.10
Requires-Dist: scanpy>=1.11
Requires-Dist: torch>=2.2
Requires-Dist: scikit-learn>=1.3
Requires-Dist: h5py>=3.10
Requires-Dist: pyyaml>=6.0
Requires-Dist: matplotlib>=3.8
Requires-Dist: seaborn>=0.13
Requires-Dist: igraph>=0.11
Requires-Dist: leidenalg>=0.10
Requires-Dist: tqdm>=4.66
Requires-Dist: openpyxl>=3.1
Provides-Extra: bench
Requires-Dist: harmonypy>=0.0.9; extra == "bench"
Dynamic: license-file
